interaktiv/__init__.py
interaktiv/alttextgenerator/__init__.py
interaktiv/alttextgenerator/configure.zcml
interaktiv/alttextgenerator/dependencies.zcml
interaktiv/alttextgenerator/exc.py
interaktiv/alttextgenerator/helper.py
interaktiv/alttextgenerator/interfaces.py
interaktiv/alttextgenerator/permissions.zcml
interaktiv/alttextgenerator/profiles.zcml
interaktiv/alttextgenerator/testing.py
interaktiv/alttextgenerator/behaviors/__init__.py
interaktiv/alttextgenerator/behaviors/alt_text_metadata.py
interaktiv/alttextgenerator/behaviors/configure.zcml
interaktiv/alttextgenerator/controlpanels/__init__.py
interaktiv/alttextgenerator/controlpanels/alttextgenerator_settings.py
interaktiv/alttextgenerator/controlpanels/configure.zcml
interaktiv/alttextgenerator/indexers/__init__.py
interaktiv/alttextgenerator/indexers/alt_text_metadata.py
interaktiv/alttextgenerator/indexers/configure.zcml
interaktiv/alttextgenerator/locales/__init__.py
interaktiv/alttextgenerator/locales/__main__.py
interaktiv/alttextgenerator/locales/interaktiv.alttextgenerator.pot
interaktiv/alttextgenerator/locales/de/LC_MESSAGES/interaktiv.alttextgenerator.mo
interaktiv/alttextgenerator/locales/de/LC_MESSAGES/interaktiv.alttextgenerator.po
interaktiv/alttextgenerator/locales/en/LC_MESSAGES/interaktiv.alttextgenerator.mo
interaktiv/alttextgenerator/locales/en/LC_MESSAGES/interaktiv.alttextgenerator.po
interaktiv/alttextgenerator/profiles/default/browserlayer.xml
interaktiv/alttextgenerator/profiles/default/catalog.xml
interaktiv/alttextgenerator/profiles/default/controlpanel.xml
interaktiv/alttextgenerator/profiles/default/metadata.xml
interaktiv/alttextgenerator/profiles/default/rolemap.xml
interaktiv/alttextgenerator/profiles/default/types.xml
interaktiv/alttextgenerator/profiles/default/registry/main.xml
interaktiv/alttextgenerator/profiles/default/types/Image.xml
interaktiv/alttextgenerator/profiles/migration/metadata.xml
interaktiv/alttextgenerator/profiles/uninstall/browserlayer.xml
interaktiv_alttextgenerator-1.0.0.dist-info/METADATA
interaktiv_alttextgenerator-1.0.0.dist-info/WHEEL
interaktiv_alttextgenerator-1.0.0.dist-info/entry_points.txt
interaktiv_alttextgenerator-1.0.0.dist-info/licenses/LICENSE.md
interaktiv_alttextgenerator-1.0.0.dist-info/RECORD
